{
    "type": "graph",
    "id": "iflink",
    "description": "Network interface tx/rx and errors",
    "version": "0.1.0",
    "notes": [
        "Graphs with variable metrics use regular expressions for the datapoint",
        "metric_name. The regular expression should include a grouping ().",
        "What is matched by the first matched group will be available for use",
        "in interpolated fields as '{{=cosi.graph_item}}'.",
        "",
        "Filters (include/exclude) work by matching the value used as graph_item",
        "this is an equality test not a regular expression. The strings in filter",
        "lists are evaluated using '==='."
    ],
    "variable_metrics": true,
    "filter": {
        "exclude": ["lo","lo0"],
        "include": null
    },
    "graphs": [
        {
            "access_keys": [],
            "composites": [],
            "datapoints": [
                {
                    "alpha": "0.3",
                    "axis": "l",
                    "check_id": null,
                    "color": "#657aa6",
                    "data_formula": "=VAL*8",
                    "derive": "counter",
                    "hidden": false,
                    "legend_formula": "=round(auto(VAL * 8),2)",
                    "metric_name": "if`([^`]+):rbytes",
                    "metric_type": "numeric",
                    "name": "%rx bps",
                    "stack": null
                },
                {
                    "alpha": "0.3",
                    "axis": "l",
                    "check_id": null,
                    "color": "#4fa18e",
                    "data_formula": "=-1 * (VAL * 8)",
                    "derive": "counter",
                    "hidden": false,
                    "legend_formula": "=round(auto(VAL * 8), 2)",
                    "metric_name": "if`([^`]+):obytes",
                    "metric_type": "numeric",
                    "name": "tx bps",
                    "stack": null
                }
            ],
            "description": "Network interface tx/rx bps for {{=cosi.graph_item}}",
            "guides": [],
            "line_style": "interpolated",
            "logarithmic_left_y": null,
            "logarithmic_right_y": null,
            "max_left_y": null,
            "max_right_y": null,
            "metric_clusters": [],
            "min_left_y": null,
            "min_right_y": null,
            "notes": null,
            "style": "area",
            "tags": ["network:bandwidth"],
            "title": "{{=cosi.host_name}} {{=cosi.graph_item}} bps"
        },
        {
            "access_keys": [],
            "composites": [],
            "datapoints": [
                {
                    "alpha": "0.3",
                    "axis": "l",
                    "check_id": null,
                    "color": "#657aa6",
                    "data_formula": "=-1 * VAL",
                    "derive": "counter",
                    "hidden": false,
                    "legend_formula": null,
                    "metric_name": "if`([^`]+):rxsdrops",
                    "metric_type": "numeric",
                    "name": "rx drops",
                    "stack": null
                },
                {
                    "alpha": "0.3",
                    "axis": "l",
                    "check_id": null,
                    "color": "#4fa18e",
                    "data_formula": null,
                    "derive": "counter",
                    "hidden": false,
                    "legend_formula": null,
                    "metric_name": "if`([^`]+):oerrors",
                    "metric_type": "numeric",
                    "name": "tx errors",
                    "stack": null
                }
            ],
            "description": "Network interface errors for {{=cosi.graph_item}}",
            "guides": [],
            "line_style": "interpolated",
            "logarithmic_left_y": null,
            "logarithmic_right_y": null,
            "max_left_y": null,
            "max_right_y": null,
            "metric_clusters": [],
            "min_left_y": null,
            "min_right_y": null,
            "notes": null,
            "style": "area",
            "tags": [],
            "title": "{{=cosi.host_name}} {{=cosi.graph_item}} Errors"
        }
    ]
}
